Metadata-Version: 2.1
Name: perceptron-pypi-YashAmin-01
Version: 0.0.1
Summary: implementation of perceptron
Home-page: https://github.com/YashAmin-01/perceptron_pypi
Author: YashAmin-01
Author-email: yashamin26@gmail.com
License: UNKNOWN
Project-URL: Bug Tracker, https://github.com/YashAmin-01/perceptron_pypi/issues
Platform: UNKNOWN
Classifier: Programming Language :: Python :: 3
Classifier: License :: OSI Approved :: MIT License
Classifier: Operating System :: OS Independent
Requires-Python: >=3.7
License-File: LICENSE
Requires-Dist: numpy
Requires-Dist: tqdm
